penguin/__init__.py
penguin/_version.py
penguin/api_client.py
penguin/config.example.yml
penguin/config.py
penguin/config_sample_fast_startup.yml
penguin/core.py
penguin/engine.py
penguin/prompt_actions.py
penguin/prompt_workflow.py
penguin/requirements.txt
penguin/run_mode.py
penguin/system_prompt.py
penguin/workspace.py
penguin/agent/__init__.py
penguin/api/__init__.py
penguin/api/routes.py
penguin/api/server.py
penguin/cli/CLI_PROTOTYPE_README.md
penguin/cli/__init__.py
penguin/cli/__main__.py
penguin/cli/cli.py
penguin/cli/cli_commands.yml
penguin/cli/cli_new.py
penguin/cli/cli_prototype_mock.py
penguin/cli/cli_simple.py
penguin/cli/command_registry.py
penguin/cli/commands.py
penguin/cli/commands.yml
penguin/cli/events.py
penguin/cli/interface.py
penguin/cli/layout_probe.py
penguin/cli/model_selector.py
penguin/cli/renderer.py
penguin/cli/shared_parser.py
penguin/cli/streaming_display.py
penguin/cli/textual_cli.py
penguin/cli/tui.css
penguin/cli/tui.py
penguin/cli/tui_commands.yml
penguin/cli/tui_prototype_mock.py
penguin/cli/typer_bridge.py
penguin/cli/ui.py
penguin/cli/widgets/__init__.py
penguin/cli/widgets/base.py
penguin/cli/widgets/streaming.py
penguin/cli/widgets/tool_execution.py
penguin/cli/widgets/unified_display.py
penguin/cognition/__init__.py
penguin/cognition/cognition.py
penguin/cognition/placeholder.md
penguin/cognition/verification.py
penguin/integrations/__init__.py
penguin/integrations/mcp/__init__.py
penguin/integrations/mcp/adapter.py
penguin/integrations/mcp/auth.py
penguin/integrations/mcp/client.py
penguin/integrations/mcp/config.yml
penguin/integrations/mcp/echo.py
penguin/integrations/mcp/http_server.py
penguin/integrations/mcp/run_echo_server.py
penguin/integrations/mcp/server.py
penguin/integrations/mcp/stdio_server.py
penguin/interfaces/web.py
penguin/llm/OPENROUTER_GUIDE.md
penguin/llm/README.md
penguin/llm/REASONING_TOKENS.md
penguin/llm/__init__.py
penguin/llm/api_client.py
penguin/llm/debug_utils.py
penguin_ai-0.4.0.dist-info/METADATA
penguin_ai-0.4.0.dist-info/WHEEL
penguin_ai-0.4.0.dist-info/entry_points.txt
penguin_ai-0.4.0.dist-info/top_level.txt
penguin_ai-0.4.0.dist-info/RECORD
