Metadata-Version: 2.2
Name: penguin-ai
Version: 0.4.0
Summary: Penguin: A modular, extensible AI coding agent and software engineer with its own execution environment.
Author-email: Maximus Putnam <MaximusPutnam@gmail.com>
Maintainer-email: Maximus Putnam <MaximusPutnam@gmail.com>
License: AGPL-3.0-or-later
Project-URL: Homepage, https://github.com/Maximooch/penguin
Project-URL: Repository, https://github.com/Maximooch/penguin
Project-URL: Documentation, https://penguin-rho.vercel.app
Project-URL: Bug Tracker, https://github.com/Maximooch/penguin/issues
Keywords: ai,agent,ai-agent,llm,llm-agent,assistant,cognitive-architecture,code-generation,developer-tool
Classifier: Development Status :: 3 - Alpha
Classifier: Programming Language :: Python :: 3
Classifier: Programming Language :: Python :: 3.9
Classifier: Programming Language :: Python :: 3.10
Classifier: Programming Language :: Python :: 3.11
Classifier: Programming Language :: Python :: 3.12
Classifier: License :: OSI Approved :: GNU Affero General Public License v3 or later (AGPLv3+)
Classifier: Operating System :: OS Independent
Classifier: Intended Audience :: Developers
Classifier: Topic :: Software Development :: Libraries :: Application Frameworks
Classifier: Topic :: Scientific/Engineering :: Artificial Intelligence
Classifier: Topic :: Software Development :: Code Generators
Requires-Python: >=3.9
Requires-Dist: tenacity>=8.0.1
Requires-Dist: pydantic>=1.8.2
Requires-Dist: python-dotenv>=0.19.0
Requires-Dist: pyyaml>=5.4.0
Requires-Dist: httpx>=0.24.0
Requires-Dist: requests>=2.26.0
Requires-Dist: litellm>=1.0.0
Requires-Dist: anthropic>=0.3.0
Requires-Dist: openai>=1.12.0
Requires-Dist: ollama
Requires-Dist: rich>=10.0.0
Requires-Dist: typer>=0.4.0
Requires-Dist: questionary>=1.10.0
Requires-Dist: textual
Requires-Dist: IPython
Requires-Dist: ipykernel
Requires-Dist: ipywidgets
Requires-Dist: plotext
Requires-Dist: matplotlib
Requires-Dist: networkx
Requires-Dist: watchdog>=2.3.0
Requires-Dist: PyGithub>=1.55
Requires-Dist: GitPython>=3.1.0
Requires-Dist: Pillow>=8.3.0
Requires-Dist: numpy>=1.20.0
Requires-Dist: pandas>=1.3.0
Provides-Extra: web
Requires-Dist: fastapi<1.0,>=0.68.0; extra == "web"
Requires-Dist: uvicorn>=0.15.0; extra == "web"
Requires-Dist: websockets>=10.0; extra == "web"
Requires-Dist: jinja2>=3.0.0; extra == "web"
Requires-Dist: python-multipart>=0.0.7; extra == "web"
Provides-Extra: mcp
Requires-Dist: pyjwt[crypto]>=2.8.0; extra == "mcp"
Requires-Dist: requests-oauthlib>=1.3.1; extra == "mcp"
Provides-Extra: minimal
Requires-Dist: tenacity>=8.0.1; extra == "minimal"
Requires-Dist: pydantic>=1.8.2; extra == "minimal"
Requires-Dist: python-dotenv>=0.19.0; extra == "minimal"
Requires-Dist: pyyaml>=5.4.0; extra == "minimal"
Requires-Dist: httpx>=0.24.0; extra == "minimal"
Requires-Dist: litellm>=1.0.0; extra == "minimal"
Requires-Dist: anthropic>=0.3.0; extra == "minimal"
Requires-Dist: openai>=1.12.0; extra == "minimal"
Provides-Extra: memory-lance
Requires-Dist: lancedb>=0.5.4; extra == "memory-lance"
Requires-Dist: pyarrow>=15.0.0; extra == "memory-lance"
Provides-Extra: memory-faiss
Requires-Dist: faiss-cpu>=1.7.4; extra == "memory-faiss"
Requires-Dist: numpy>=1.20.0; extra == "memory-faiss"
Requires-Dist: sentence-transformers>=2.3.0; extra == "memory-faiss"
Provides-Extra: memory-chroma
Requires-Dist: chromadb>=0.4.22; extra == "memory-chroma"
Provides-Extra: llm-transformers
Requires-Dist: transformers>=4.38.0; extra == "llm-transformers"
Requires-Dist: torch>=2.0.0; extra == "llm-transformers"
Requires-Dist: accelerate>=0.25.0; extra == "llm-transformers"
Requires-Dist: bitsandbytes>=0.43.0; sys_platform != "darwin" and extra == "llm-transformers"
Requires-Dist: sentence-transformers>=2.3.0; extra == "llm-transformers"
Provides-Extra: llm-ollama
Requires-Dist: ollama>=0.1.7; extra == "llm-ollama"
Provides-Extra: pydoll
Requires-Dist: pydoll-python>=2.0.0; python_version >= "3.10" and extra == "pydoll"
Provides-Extra: browser
Requires-Dist: browser_use>=0.1.0; python_version >= "3.11" and extra == "browser"
Requires-Dist: playwright>=1.40.0; extra == "browser"
Requires-Dist: pillow>=8.3.0; extra == "browser"
Provides-Extra: dev
Requires-Dist: pytest>=6.0.0; extra == "dev"
Requires-Dist: pytest-asyncio>=0.21.0; extra == "dev"
Requires-Dist: black>=21.0.0; extra == "dev"
Requires-Dist: isort>=5.0.0; extra == "dev"
Requires-Dist: ruff>=0.1.0; extra == "dev"
Requires-Dist: build; extra == "dev"
Requires-Dist: twine>=5.0.0; extra == "dev"
Requires-Dist: wheel>=0.40.0; extra == "dev"
Requires-Dist: setuptools<77,>=76.1; extra == "dev"
Requires-Dist: pre-commit; extra == "dev"
Requires-Dist: pydoll-python>=2.0.0; python_version >= "3.10" and extra == "dev"
Provides-Extra: test
Requires-Dist: pytest>=6.0.0; extra == "test"
Requires-Dist: pytest-asyncio>=0.21.0; extra == "test"
Requires-Dist: pytest-cov>=4.0.0; extra == "test"
Provides-Extra: all
Requires-Dist: penguin-ai[browser,llm_ollama,llm_transformers,memory_chroma,memory_faiss,memory_lance,pydoll,web]; extra == "all"
